{
  "version": 1,
  "files": {
    "../../../../tmp/pi-agent-3ca218a6-0114-434-6373ee43/src/gitnexus.ts": {
      "latest": {
        "commit": "030179d",
        "timestamp": "2026-05-17T22:51:47.749Z",
        "mi": 26.2,
        "cognitive": 284,
        "nesting": 7,
        "lines": 356,
        "maxCyclomatic": 87,
        "entropy": 6.65
      },
      "history": [
        {
          "commit": "030179d",
          "timestamp": "2026-05-17T22:51:47.749Z",
          "mi": 26.2,
          "cognitive": 284,
          "nesting": 7,
          "lines": 356,
          "maxCyclomatic": 87,
          "entropy": 6.65
        }
      ],
      "trend": "stable"
    },
    "../../../../tmp/pi-agent-3ca218a6-0114-434-6373ee43/tests/config.test.ts": {
      "latest": {
        "commit": "030179d",
        "timestamp": "2026-05-17T22:51:47.778Z",
        "mi": 55.8,
        "cognitive": 10,
        "nesting": 5,
        "lines": 35,
        "maxCyclomatic": 20,
        "entropy": 4.69
      },
      "history": [
        {
          "commit": "030179d",
          "timestamp": "2026-05-17T22:51:47.778Z",
          "mi": 55.8,
          "cognitive": 10,
          "nesting": 5,
          "lines": 35,
          "maxCyclomatic": 20,
          "entropy": 4.69
        }
      ],
      "trend": "stable"
    },
    "../../../../tmp/pi-agent-3ca218a6-0114-434-6373ee43/src/mcp-client.ts": {
      "latest": {
        "commit": "030179d",
        "timestamp": "2026-05-17T22:51:51.809Z",
        "mi": 34.5,
        "cognitive": 54,
        "nesting": 5,
        "lines": 211,
        "maxCyclomatic": 14,
        "entropy": 6.56
      },
      "history": [
        {
          "commit": "030179d",
          "timestamp": "2026-05-17T22:51:51.809Z",
          "mi": 34.5,
          "cognitive": 54,
          "nesting": 5,
          "lines": 211,
          "maxCyclomatic": 14,
          "entropy": 6.56
        }
      ],
      "trend": "stable"
    },
    "../../../../tmp/pi-agent-3ca218a6-0114-434-6373ee43/tests/gitnexus.test.ts": {
      "latest": {
        "commit": "030179d",
        "timestamp": "2026-05-17T22:51:58.165Z",
        "mi": 30.6,
        "cognitive": 0,
        "nesting": 3,
        "lines": 129,
        "maxCyclomatic": 1,
        "entropy": 3.78
      },
      "history": [
        {
          "commit": "030179d",
          "timestamp": "2026-05-17T22:51:58.165Z",
          "mi": 30.6,
          "cognitive": 0,
          "nesting": 3,
          "lines": 129,
          "maxCyclomatic": 1,
          "entropy": 3.78
        }
      ],
      "trend": "stable"
    },
    "../../../../tmp/pi-agent-e6240138-6ff6-4b8-2ce174f7/src/tools.ts": {
      "latest": {
        "commit": "030179d",
        "timestamp": "2026-05-17T22:52:21.919Z",
        "mi": 19.7,
        "cognitive": 107,
        "nesting": 4,
        "lines": 273,
        "maxCyclomatic": 36,
        "entropy": 6.28
      },
      "history": [
        {
          "commit": "030179d",
          "timestamp": "2026-05-17T22:52:21.919Z",
          "mi": 19.7,
          "cognitive": 107,
          "nesting": 4,
          "lines": 273,
          "maxCyclomatic": 36,
          "entropy": 6.28
        }
      ],
      "trend": "stable"
    },
    "../../../../tmp/pi-agent-e6240138-6ff6-4b8-2ce174f7/tests/tools.test.ts": {
      "latest": {
        "commit": "030179d",
        "timestamp": "2026-05-17T22:52:21.934Z",
        "mi": 22.9,
        "cognitive": 15,
        "nesting": 3,
        "lines": 235,
        "maxCyclomatic": 11,
        "entropy": 5.37
      },
      "history": [
        {
          "commit": "030179d",
          "timestamp": "2026-05-17T22:52:21.934Z",
          "mi": 22.9,
          "cognitive": 15,
          "nesting": 3,
          "lines": 235,
          "maxCyclomatic": 11,
          "entropy": 5.37
        }
      ],
      "trend": "stable"
    },
    "../../../../tmp/pi-agent-e6240138-6ff6-4b8-2ce174f7/src/mcp-client.ts": {
      "latest": {
        "commit": "030179d",
        "timestamp": "2026-05-17T22:52:26.755Z",
        "mi": 34.5,
        "cognitive": 54,
        "nesting": 5,
        "lines": 211,
        "maxCyclomatic": 14,
        "entropy": 6.56
      },
      "history": [
        {
          "commit": "030179d",
          "timestamp": "2026-05-17T22:52:26.755Z",
          "mi": 34.5,
          "cognitive": 54,
          "nesting": 5,
          "lines": 211,
          "maxCyclomatic": 14,
          "entropy": 6.56
        }
      ],
      "trend": "stable"
    },
    "src/index.ts": {
      "latest": {
        "commit": "cd61401",
        "timestamp": "2026-05-17T23:00:27.310Z",
        "mi": 17.9,
        "cognitive": 351,
        "nesting": 6,
        "lines": 495,
        "maxCyclomatic": 208,
        "entropy": 6.63
      },
      "history": [
        {
          "commit": "40a4a98",
          "timestamp": "2026-05-17T22:56:09.691Z",
          "mi": 22.8,
          "cognitive": 249,
          "nesting": 5,
          "lines": 376,
          "maxCyclomatic": 144,
          "entropy": 6.53
        },
        {
          "commit": "cd61401",
          "timestamp": "2026-05-17T23:00:27.310Z",
          "mi": 17.9,
          "cognitive": 351,
          "nesting": 6,
          "lines": 495,
          "maxCyclomatic": 208,
          "entropy": 6.63
        }
      ],
      "trend": "regressing"
    },
    "src/ui/main-menu.ts": {
      "latest": {
        "commit": "cd61401",
        "timestamp": "2026-05-17T23:00:33.545Z",
        "mi": 30.8,
        "cognitive": 56,
        "nesting": 4,
        "lines": 163,
        "maxCyclomatic": 20,
        "entropy": 6.02
      },
      "history": [
        {
          "commit": "40a4a98",
          "timestamp": "2026-05-17T22:56:09.712Z",
          "mi": 36.3,
          "cognitive": 24,
          "nesting": 3,
          "lines": 113,
          "maxCyclomatic": 7,
          "entropy": 5.87
        },
        {
          "commit": "cd61401",
          "timestamp": "2026-05-17T23:00:33.545Z",
          "mi": 30.8,
          "cognitive": 56,
          "nesting": 4,
          "lines": 163,
          "maxCyclomatic": 20,
          "entropy": 6.02
        }
      ],
      "trend": "regressing"
    },
    "src/ui/settings-menu.ts": {
      "latest": {
        "commit": "cd61401",
        "timestamp": "2026-05-17T23:00:33.567Z",
        "mi": 24.4,
        "cognitive": 67,
        "nesting": 4,
        "lines": 229,
        "maxCyclomatic": 92,
        "entropy": 5.49
      },
      "history": [
        {
          "commit": "40a4a98",
          "timestamp": "2026-05-17T22:56:09.725Z",
          "mi": 32.4,
          "cognitive": 36,
          "nesting": 4,
          "lines": 137,
          "maxCyclomatic": 48,
          "entropy": 5.49
        },
        {
          "commit": "cd61401",
          "timestamp": "2026-05-17T23:00:33.567Z",
          "mi": 24.4,
          "cognitive": 67,
          "nesting": 4,
          "lines": 229,
          "maxCyclomatic": 92,
          "entropy": 5.49
        }
      ],
      "trend": "regressing"
    },
    "src/server-api.ts": {
      "latest": {
        "commit": "cd61401",
        "timestamp": "2026-05-17T23:00:27.359Z",
        "mi": 40,
        "cognitive": 29,
        "nesting": 4,
        "lines": 147,
        "maxCyclomatic": 7,
        "entropy": 5.98
      },
      "history": [
        {
          "commit": "40a4a98",
          "timestamp": "2026-05-17T22:56:09.738Z",
          "mi": 40,
          "cognitive": 29,
          "nesting": 4,
          "lines": 147,
          "maxCyclomatic": 7,
          "entropy": 5.98
        },
        {
          "commit": "cd61401",
          "timestamp": "2026-05-17T23:00:27.359Z",
          "mi": 40,
          "cognitive": 29,
          "nesting": 4,
          "lines": 147,
          "maxCyclomatic": 7,
          "entropy": 5.98
        }
      ],
      "trend": "stable"
    },
    "src/gitnexus.ts": {
      "latest": {
        "commit": "cd61401",
        "timestamp": "2026-05-17T23:00:27.329Z",
        "mi": 25.2,
        "cognitive": 296,
        "nesting": 7,
        "lines": 383,
        "maxCyclomatic": 87,
        "entropy": 6.68
      },
      "history": [
        {
          "commit": "40a4a98",
          "timestamp": "2026-05-17T22:56:09.756Z",
          "mi": 25.2,
          "cognitive": 296,
          "nesting": 7,
          "lines": 383,
          "maxCyclomatic": 87,
          "entropy": 6.68
        },
        {
          "commit": "cd61401",
          "timestamp": "2026-05-17T23:00:27.329Z",
          "mi": 25.2,
          "cognitive": 296,
          "nesting": 7,
          "lines": 383,
          "maxCyclomatic": 87,
          "entropy": 6.68
        }
      ],
      "trend": "stable"
    },
    "src/mcp-client.ts": {
      "latest": {
        "commit": "cd61401",
        "timestamp": "2026-05-17T23:00:27.345Z",
        "mi": 34.5,
        "cognitive": 54,
        "nesting": 5,
        "lines": 211,
        "maxCyclomatic": 14,
        "entropy": 6.56
      },
      "history": [
        {
          "commit": "40a4a98",
          "timestamp": "2026-05-17T22:56:09.769Z",
          "mi": 34.5,
          "cognitive": 54,
          "nesting": 5,
          "lines": 211,
          "maxCyclomatic": 14,
          "entropy": 6.56
        },
        {
          "commit": "cd61401",
          "timestamp": "2026-05-17T23:00:27.345Z",
          "mi": 34.5,
          "cognitive": 54,
          "nesting": 5,
          "lines": 211,
          "maxCyclomatic": 14,
          "entropy": 6.56
        }
      ],
      "trend": "stable"
    },
    "src/tools.ts": {
      "latest": {
        "commit": "cd61401",
        "timestamp": "2026-05-17T23:00:27.382Z",
        "mi": 15.5,
        "cognitive": 133,
        "nesting": 4,
        "lines": 375,
        "maxCyclomatic": 55,
        "entropy": 6.14
      },
      "history": [
        {
          "commit": "40a4a98",
          "timestamp": "2026-05-17T22:56:13.788Z",
          "mi": 15.5,
          "cognitive": 133,
          "nesting": 4,
          "lines": 375,
          "maxCyclomatic": 55,
          "entropy": 6.14
        },
        {
          "commit": "cd61401",
          "timestamp": "2026-05-17T23:00:27.382Z",
          "mi": 15.5,
          "cognitive": 133,
          "nesting": 4,
          "lines": 375,
          "maxCyclomatic": 55,
          "entropy": 6.14
        }
      ],
      "trend": "stable"
    },
    "tests/index-command.test.ts": {
      "latest": {
        "commit": "cd61401",
        "timestamp": "2026-05-17T23:00:27.251Z",
        "mi": 41,
        "cognitive": 0,
        "nesting": 2,
        "lines": 56,
        "maxCyclomatic": 1,
        "entropy": 5.29
      },
      "history": [
        {
          "commit": "cd61401",
          "timestamp": "2026-05-17T23:00:27.251Z",
          "mi": 41,
          "cognitive": 0,
          "nesting": 2,
          "lines": 56,
          "maxCyclomatic": 1,
          "entropy": 5.29
        }
      ],
      "trend": "stable"
    },
    "tests/augment-hook.test.ts": {
      "latest": {
        "commit": "cd61401",
        "timestamp": "2026-05-17T23:00:27.270Z",
        "mi": 27.2,
        "cognitive": 8,
        "nesting": 3,
        "lines": 187,
        "maxCyclomatic": 4,
        "entropy": 5.43
      },
      "history": [
        {
          "commit": "cd61401",
          "timestamp": "2026-05-17T23:00:27.270Z",
          "mi": 27.2,
          "cognitive": 8,
          "nesting": 3,
          "lines": 187,
          "maxCyclomatic": 4,
          "entropy": 5.43
        }
      ],
      "trend": "stable"
    },
    "tests/mcp-client.test.ts": {
      "latest": {
        "commit": "cd61401",
        "timestamp": "2026-05-17T23:00:33.458Z",
        "mi": 36.4,
        "cognitive": 0,
        "nesting": 3,
        "lines": 115,
        "maxCyclomatic": 2,
        "entropy": 5.96
      },
      "history": [
        {
          "commit": "cd61401",
          "timestamp": "2026-05-17T23:00:33.458Z",
          "mi": 36.4,
          "cognitive": 0,
          "nesting": 3,
          "lines": 115,
          "maxCyclomatic": 2,
          "entropy": 5.96
        }
      ],
      "trend": "stable"
    },
    "tests/tools.test.ts": {
      "latest": {
        "commit": "cd61401",
        "timestamp": "2026-05-17T23:00:33.475Z",
        "mi": 20.4,
        "cognitive": 15,
        "nesting": 3,
        "lines": 287,
        "maxCyclomatic": 18,
        "entropy": 5.38
      },
      "history": [
        {
          "commit": "cd61401",
          "timestamp": "2026-05-17T23:00:33.475Z",
          "mi": 20.4,
          "cognitive": 15,
          "nesting": 3,
          "lines": 287,
          "maxCyclomatic": 18,
          "entropy": 5.38
        }
      ],
      "trend": "stable"
    },
    "tests/config.test.ts": {
      "latest": {
        "commit": "cd61401",
        "timestamp": "2026-05-17T23:00:33.489Z",
        "mi": 43.6,
        "cognitive": 20,
        "nesting": 5,
        "lines": 79,
        "maxCyclomatic": 47,
        "entropy": 4.92
      },
      "history": [
        {
          "commit": "cd61401",
          "timestamp": "2026-05-17T23:00:33.489Z",
          "mi": 43.6,
          "cognitive": 20,
          "nesting": 5,
          "lines": 79,
          "maxCyclomatic": 47,
          "entropy": 4.92
        }
      ],
      "trend": "stable"
    },
    "tests/gitnexus.test.ts": {
      "latest": {
        "commit": "cd61401",
        "timestamp": "2026-05-17T23:00:33.503Z",
        "mi": 30.6,
        "cognitive": 0,
        "nesting": 3,
        "lines": 129,
        "maxCyclomatic": 1,
        "entropy": 3.78
      },
      "history": [
        {
          "commit": "cd61401",
          "timestamp": "2026-05-17T23:00:33.503Z",
          "mi": 30.6,
          "cognitive": 0,
          "nesting": 3,
          "lines": 129,
          "maxCyclomatic": 1,
          "entropy": 3.78
        }
      ],
      "trend": "stable"
    },
    "tests/autocomplete.test.ts": {
      "latest": {
        "commit": "cd61401",
        "timestamp": "2026-05-17T23:00:33.516Z",
        "mi": 35.2,
        "cognitive": 0,
        "nesting": 3,
        "lines": 84,
        "maxCyclomatic": 1,
        "entropy": 5.08
      },
      "history": [
        {
          "commit": "cd61401",
          "timestamp": "2026-05-17T23:00:33.516Z",
          "mi": 35.2,
          "cognitive": 0,
          "nesting": 3,
          "lines": 84,
          "maxCyclomatic": 1,
          "entropy": 5.08
        }
      ],
      "trend": "stable"
    }
  },
  "capturedAt": "2026-05-17T23:00:38.567Z"
}